{
    "pose": [
        {
            "x": 0.0, 
            "y": 0.0
        }, 
        {
            "x": 0.0, 
            "y": 0.0
        }, 
        {
            "x": 0.0, 
            "y": 0.0
        }, 
        {
            "x": -0.04999957662340228, 
            "y": 0.00020576073610861957
        }, 
        {
            "x": -0.04999957662340228, 
            "y": 0.00020576073610861957
        }, 
        {
            "x": -0.04999957662340228, 
            "y": 0.00020576073610861957
        }, 
        {
            "x": -0.04999957662340228, 
            "y": 0.00020576073610861957
        }, 
        {
            "x": -0.04999957662340228, 
            "y": 0.00020576073610861957
        }, 
        {
            "x": -0.04999957662340228, 
            "y": 0.00020576073610861957
        }, 
        {
            "x": -0.04999957662340228, 
            "y": 0.00020576073610861957
        }, 
        {
            "x": -0.04999957662340228, 
            "y": 0.00020576073610861957
        }, 
        {
            "x": -0.04999957662340228, 
            "y": 0.00020576073610861957
        }, 
        {
            "x": 2.7999762909105277, 
            "y": -0.011522601222082696
        }, 
        {
            "x": 14.899873833773878, 
            "y": -0.06131669936036863
        }, 
        {
            "x": 27.249769259754242, 
            "y": -0.11213960117919766
        }, 
        {
            "x": 39.99966129872182, 
            "y": -0.16460858888689564
        }, 
        {
            "x": 60.749485597433775, 
            "y": -0.24999929437197274
        }, 
        {
            "x": 79.34932810133941, 
            "y": -0.32654228820437925
        }, 
        {
            "x": 98.4991659481025, 
            "y": -0.40534865013398047
        }, 
        {
            "x": 122.78605694743473, 
            "y": 6.6824525312307115
        }, 
        {
            "x": 131.93716059289312, 
            "y": 18.441164283377642
        }, 
        {
            "x": 132.90561337609418, 
            "y": 32.50786607188194
        }, 
        {
            "x": 124.50208107471641, 
            "y": 45.29342999607789
        }, 
        {
            "x": 124.50208107471641, 
            "y": 45.29342999607789
        }, 
        {
            "x": 124.02964473020677, 
            "y": 45.663300108936916
        }, 
        {
            "x": 122.57980322988988, 
            "y": 45.64186126664371
        }, 
        {
            "x": 120.77972777132133, 
            "y": 44.466179190800396
        }, 
        {
            "x": 118.26885769180072, 
            "y": 42.32479378789692
        }, 
        {
            "x": 114.92157587263077, 
            "y": 40.99976381727198
        }, 
        {
            "x": 110.85770263528416, 
            "y": 40.15867267430477
        }, 
        {
            "x": 106.74062598109342, 
            "y": 38.46983288808538
        }, 
        {
            "x": 103.07667802953674, 
            "y": 36.03354772245234
        }, 
        {
            "x": 99.01370499322645, 
            "y": 33.87664018938201
        }, 
        {
            "x": 94.91297013996291, 
            "y": 32.76018434017451
        }, 
        {
            "x": 90.64942946098091, 
            "y": 31.485538946872634
        }, 
        {
            "x": 87.02391951669249, 
            "y": 29.36523763718438
        }, 
        {
            "x": 83.40016918817787, 
            "y": 27.14466708964706
        }, 
        {
            "x": 79.37611783294903, 
            "y": 25.777366577513398
        }, 
        {
            "x": 75.13544372276165, 
            "y": 24.604045184549655
        }, 
        {
            "x": 71.26023143118057, 
            "y": 22.627879782773054
        }, 
        {
            "x": 67.43302746916214, 
            "y": 20.260917629904856
        }, 
        {
            "x": 63.25577660277246, 
            "y": 18.58742571201381
        }, 
        {
            "x": 58.76909023390764, 
            "y": 17.36589166523384
        }, 
        {
            "x": 54.51959047071441, 
            "y": 15.477969060193919
        }, 
        {
            "x": 50.49007997330234, 
            "y": 12.962905412640257
        }, 
        {
            "x": 46.12502316401978, 
            "y": 10.848956725529817
        }, 
        {
            "x": 41.77824066150601, 
            "y": 9.68470508785
        }, 
        {
            "x": 37.45823680673262, 
            "y": 8.25639605450215
        }, 
        {
            "x": 33.9287042639823, 
            "y": 6.0735309579681465
        }, 
        {
            "x": 30.314122744298224, 
            "y": 3.838066702481514
        }, 
        {
            "x": 26.520447710786733, 
            "y": 2.737825937870617
        }, 
        {
            "x": 22.564934733326176, 
            "y": 1.8681035194283204
        }, 
        {
            "x": 19.487690505550564, 
            "y": -0.00020265532507934836
        }, 
        {
            "x": 18.93790325000308, 
            "y": -1.4494210562700736
        }, 
        {
            "x": 18.963904075472126, 
            "y": -1.4921288667375774
        }, 
        {
            "x": 19.01357689973974, 
            "y": -1.497839429693975
        }, 
        {
            "x": 19.058433653726063, 
            "y": -1.4757516135545212
        }, 
        {
            "x": 19.058433653726063, 
            "y": -1.4757516135545212
        }, 
        {
            "x": 16.558463428211912, 
            "y": -1.4879529062205288
        }, 
        {
            "x": 11.05868596701813, 
            "y": -1.537428934202567
        }, 
        {
            "x": 5.608687563049342, 
            "y": -1.5415998738642034
        }, 
        {
            "x": 0.15868915908055356, 
            "y": -1.5457708135258394
        }, 
        {
            "x": -2.7410615923382755, 
            "y": -1.5837915926595805
        }, 
        {
            "x": -2.7410615923382755, 
            "y": -1.5837915926595805
        }, 
        {
            "x": -2.7410615923382755, 
            "y": -1.5837915926595805
        }, 
        {
            "x": -2.7410615923382755, 
            "y": -1.5837915926595805
        }, 
        {
            "x": -2.7410615923382755, 
            "y": -1.5837915926595805
        }, 
        {
            "x": -2.691072978334556, 
            "y": -1.5827246015690888
        }, 
        {
            "x": -2.691072978334556, 
            "y": -1.5827246015690888
        }, 
        {
            "x": -2.691072978334556, 
            "y": -1.5827246015690888
        }, 
        {
            "x": -2.691072978334556, 
            "y": -1.5827246015690888
        }
    ]
}